jolli/__init__.py
jolli/jolliCode.py
jolli/.ipynb_checkpoints/__init__-checkpoint.py
jolli/.ipynb_checkpoints/jolliCode-checkpoint.py
jolli-0.0.18.dist-info/METADATA
jolli-0.0.18.dist-info/WHEEL
jolli-0.0.18.dist-info/licenses/LICENSE
jolli-0.0.18.dist-info/RECORD
