Metadata-Version: 2.1
Name: jolli
Version: 0.0.18
Summary: jolli is just an openPMD low-level interface for reading and plotting PIConGPU output in python. It is a simple wrapper for the openPMD-api to read PIConGPU output
Project-URL: GitHub, https://github.com/ComputationalRadiationPhysics/jolli
Author-email: Thomas Kluge <t.kluge@hzdr.de>
License-File: LICENSE
Classifier: Framework :: Jupyter
Classifier: Operating System :: OS Independent
Classifier: Programming Language :: Python :: 3
Requires-Python: >=3.6
